<?xml version="1.0" encoding="utf-8"?>
<Sprites>
	<Sprite name="Power_Cables_" x="0" y="0" w="1" h="1" pixelPerUnit="64" pivotX="0.5" pivotY="0.5" />
	<Sprite name="Power_Cables_ES" x="0" y="2" w="1" h="1" pixelPerUnit="64" pivotX="0.5" pivotY="0.5" />
	<Sprite name="Power_Cables_ESW" x="2" y="3" w="1" h="1" pixelPerUnit="64" pivotX="0.5" pivotY="0.5" />
	<Sprite name="Power_Cables_EW" x="1" y="1" w="1" h="1" pixelPerUnit="64" pivotX="0.5" pivotY="0.5" />
	<Sprite name="Power_Cables_N" x="1" y="0" w="1" h="1" pixelPerUnit="64" pivotX="0.5" pivotY="0.5" />
	<Sprite name="Power_Cables_NE" x="1" y="2" w="1" h="1" pixelPerUnit="64" pivotX="0.5" pivotY="0.5" />
	<Sprite name="Power_Cables_NES" x="1" y="3" w="1" h="1" pixelPerUnit="64" pivotX="0.5" pivotY="0.5" />
	<Sprite name="Power_Cables_NESW" x="0" y="3" w="1" h="1" pixelPerUnit="64" pivotX="0.5" pivotY="0.5" />
	<Sprite name="Power_Cables_NEW" x="0" y="1" w="1" h="1" pixelPerUnit="64" pivotX="0.5" pivotY="0.5" />
	<Sprite name="Power_Cables_NS" x="2" y="1" w="1" h="1" pixelPerUnit="64" pivotX="0.5" pivotY="0.5" />
	<Sprite name="Power_Cables_NSW" x="3" y="3" w="1" h="1" pixelPerUnit="64" pivotX="0.5" pivotY="0.5" />
	<Sprite name="Power_Cables_NW" x="3" y="1" w="1" h="1" pixelPerUnit="64" pivotX="0.5" pivotY="0.5" />
	<Sprite name="Power_Cables_S" x="3" y="2" w="1" h="1" pixelPerUnit="64" pivotX="0.5" pivotY="0.5" />
	<Sprite name="Power_Cables_SW" x="2" y="2" w="1" h="1" pixelPerUnit="64" pivotX="0.5" pivotY="0.5" />
	<Sprite name="Power_Cables_W" x="2" y="0" w="1" h="1" pixelPerUnit="64" pivotX="0.5" pivotY="0.5" />
	<Sprite name="Power_Cables_" x="3" y="0" w="1" h="1" pixelPerUnit="64" pivotX="0.5" pivotY="0.5" />
</Sprites>